words2numbers/__init__.py
words2numbers/_words2num.py
words2numbers/base.py
words2numbers/data.py
words2numbers/ejtoken.py
words2numbers/normalize.py
words2numbers/utils.py
words2numbers-5.12.22.dist-info/LICENSE
words2numbers-5.12.22.dist-info/METADATA
words2numbers-5.12.22.dist-info/WHEEL
words2numbers-5.12.22.dist-info/top_level.txt
words2numbers-5.12.22.dist-info/RECORD
