Metadata-Version: 2.1
Name: words2numbers
Version: 5.12.22
Summary: A python package for extracting numbers from text
Home-page: https://best-practice-and-impact.github.io/example-package-python/
Author: Elijah Manda
Author-email: Elijah Manda <elijahmandajc@gmail.com>
License: MIT License
Keywords: nlp,extraction,numbers
Classifier: License :: OSI Approved :: MIT License
Classifier: Programming Language :: Python
Classifier: Programming Language :: Python :: 3
Requires-Python: >=3.9
License-File: LICENSE
Requires-Dist: num2words (>=0.5.12)
Requires-Dist: loguru (>=0.6.0)
